grpc_connection_forwarder/__init__.py
grpc_connection_forwarder/connection_counter.py
grpc_connection_forwarder/grpc_connection_forwarder.py
grpc_connection_forwarder/lock_with_value.py
grpc_connection_forwarder-0.1.5.dist-info/LICENSE
grpc_connection_forwarder-0.1.5.dist-info/METADATA
grpc_connection_forwarder-0.1.5.dist-info/WHEEL
grpc_connection_forwarder-0.1.5.dist-info/top_level.txt
grpc_connection_forwarder-0.1.5.dist-info/RECORD
