Metadata-Version: 2.1
Name: grpc-connection-forwarder
Version: 0.1.5
Summary: A small package for counting gRPC connections
Home-page: https://github.com/flagman/grpc-connection-forwarder
Author: Pavel Malay
Author-email: flagmansupport@gmail.com
Classifier: Programming Language :: Python :: 3
Classifier: License :: OSI Approved :: MIT License
Classifier: Operating System :: OS Independent
License-File: LICENSE
